data_wise_gov_stats_mcp_server/__init__.py
data_wise_gov_stats_mcp_server/constants.py
data_wise_gov_stats_mcp_server/main.py
data_wise_gov_stats_mcp_server/query.py
data_wise_gov_stats_mcp_server/test_gov_stats.py
data_wise_gov_stats_mcp_server-1.1.0.dist-info/METADATA
data_wise_gov_stats_mcp_server-1.1.0.dist-info/WHEEL
data_wise_gov_stats_mcp_server-1.1.0.dist-info/entry_points.txt
data_wise_gov_stats_mcp_server-1.1.0.dist-info/licenses/LICENSE
data_wise_gov_stats_mcp_server-1.1.0.dist-info/RECORD
